cumulator/.DS_Store
cumulator/__init__.py
cumulator/base.py
cumulator/bonus.py
cumulator/cumulator.py
cumulator/helper_functions.py
cumulator/other.py
cumulator/alge/alge_test.py
cumulator/alge/data_selection.py
cumulator/countries_data/countr_2_dig.json
cumulator/countries_data/country_data.csv
cumulator/countries_data/country_dataset_adjusted.csv
cumulator/countries_data/country_dataset_helpers.py
cumulator/hardware_data/cpu.csv
cumulator/hardware_data/gpu.csv
cumulator/hardware_data/webscraper.py
cumulator/metrics_conversion_data/CO2_metrics.json
cumulator/prediction_feature/dataset.csv
cumulator/prediction_feature/prediction_helper.py
cumulator/prediction_feature/visualization_helper.py
cumulator/prediction_feature/models/F1_model_Decision_Tree.sav
cumulator/prediction_feature/models/F1_model_Linear.sav
cumulator/prediction_feature/models/F1_model_Neural_Network.sav
cumulator/prediction_feature/models/F1_model_Random_Forest.sav
cumulator/prediction_feature/models/F1_rmse.pkl
cumulator/prediction_feature/models/consumption_model_Decision_Tree.sav
cumulator/prediction_feature/models/consumption_model_Linear.sav
cumulator/prediction_feature/models/consumption_model_Neural_Network.sav
cumulator/prediction_feature/models/consumption_model_Random_Forest.sav
cumulator/prediction_feature/models/consumption_rmse.pkl
cumulator/prediction_feature/models/support_F1_Decision_Tree.pkl
cumulator/prediction_feature/models/support_F1_Linear.pkl
cumulator/prediction_feature/models/support_F1_Neural_Network.pkl
cumulator/prediction_feature/models/support_F1_Random_Forest.pkl
cumulator/prediction_feature/models/support_consumption_Decision_Tree.pkl
cumulator/prediction_feature/models/support_consumption_Linear.pkl
cumulator/prediction_feature/models/support_consumption_Neural_Network.pkl
cumulator/prediction_feature/models/support_consumption_Random_Forest.pkl
cumulator/prediction_feature/utils/mljar_dataset_adder.py
cumulator-0.1.0.dist-info/AUTHORS.rst
cumulator-0.1.0.dist-info/LICENSE
cumulator-0.1.0.dist-info/METADATA
cumulator-0.1.0.dist-info/WHEEL
cumulator-0.1.0.dist-info/top_level.txt
cumulator-0.1.0.dist-info/RECORD
